odoo/addons/ai_oca_bridge_chatter/README.rst
odoo/addons/ai_oca_bridge_chatter/__init__.py
odoo/addons/ai_oca_bridge_chatter/__manifest__.py
odoo/addons/ai_oca_bridge_chatter/i18n/ai_oca_bridge_chatter.pot
odoo/addons/ai_oca_bridge_chatter/i18n/es.po
odoo/addons/ai_oca_bridge_chatter/i18n/es_VE.po
odoo/addons/ai_oca_bridge_chatter/i18n/it.po
odoo/addons/ai_oca_bridge_chatter/i18n/pt_BR.po
odoo/addons/ai_oca_bridge_chatter/models/__init__.py
odoo/addons/ai_oca_bridge_chatter/models/ai_bridge.py
odoo/addons/ai_oca_bridge_chatter/models/ai_bridge_execution.py
odoo/addons/ai_oca_bridge_chatter/models/mail_channel.py
odoo/addons/ai_oca_bridge_chatter/models/res_partner.py
odoo/addons/ai_oca_bridge_chatter/models/res_users.py
odoo/addons/ai_oca_bridge_chatter/readme/CONFIGURE.md
odoo/addons/ai_oca_bridge_chatter/readme/CONTRIBUTORS.md
odoo/addons/ai_oca_bridge_chatter/readme/DESCRIPTION.md
odoo/addons/ai_oca_bridge_chatter/static/description/Chat.json
odoo/addons/ai_oca_bridge_chatter/static/description/icon.png
odoo/addons/ai_oca_bridge_chatter/static/description/index.html
odoo/addons/ai_oca_bridge_chatter/tests/__init__.py
odoo/addons/ai_oca_bridge_chatter/tests/test_chatter.py
odoo/addons/ai_oca_bridge_chatter/views/ai_bridge.xml
odoo/addons/ai_oca_bridge_chatter/views/res_users.xml
odoo_addon_ai_oca_bridge_chatter-18.0.2.0.0.dist-info/METADATA
odoo_addon_ai_oca_bridge_chatter-18.0.2.0.0.dist-info/WHEEL
odoo_addon_ai_oca_bridge_chatter-18.0.2.0.0.dist-info/top_level.txt
odoo_addon_ai_oca_bridge_chatter-18.0.2.0.0.dist-info/RECORD
