Metadata-Version: 2.1
Name: odoo-addon-ai_oca_bridge_chatter
Version: 18.0.2.0.0
Requires-Python: >=3.10
Requires-Dist: odoo-addon-ai_oca_bridge==18.0.*
Requires-Dist: odoo==18.0.*
Summary: Integrate a Bridge with a user that will use it on chatter
Home-page: https://github.com/OCA/ai
License: AGPL-3
Author: Dixmit,Odoo Community Association (OCA)
Author-email: support@odoo-community.org
Classifier: Programming Language :: Python
Classifier: Framework :: Odoo
Classifier: Framework :: Odoo :: 18.0
Classifier: License :: OSI Approved :: GNU Affero General Public License v3
